wagtail_seotoolkit/__init__.py
wagtail_seotoolkit/apps.py
wagtail_seotoolkit/middleware.py
wagtail_seotoolkit/models.py
wagtail_seotoolkit/views.py
wagtail_seotoolkit/wagtail_hooks.py
wagtail_seotoolkit/core/__init__.py
wagtail_seotoolkit/core/models.py
wagtail_seotoolkit/core/views.py
wagtail_seotoolkit/core/ui/__init__.py
wagtail_seotoolkit/core/ui/get_side_panels.py
wagtail_seotoolkit/core/ui/side_panels.py
wagtail_seotoolkit/core/utils/__init__.py
wagtail_seotoolkit/core/utils/pagespeed_api.py
wagtail_seotoolkit/core/utils/seo_audit.py
wagtail_seotoolkit/core/utils/seo_validators.py
wagtail_seotoolkit/core/utils/checkers/__init__.py
wagtail_seotoolkit/core/utils/checkers/base.py
wagtail_seotoolkit/core/utils/checkers/content_checker.py
wagtail_seotoolkit/core/utils/checkers/freshness_checker.py
wagtail_seotoolkit/core/utils/checkers/header_checker.py
wagtail_seotoolkit/core/utils/checkers/image_checker.py
wagtail_seotoolkit/core/utils/checkers/link_checker.py
wagtail_seotoolkit/core/utils/checkers/meta_checker.py
wagtail_seotoolkit/core/utils/checkers/mobile_checker.py
wagtail_seotoolkit/core/utils/checkers/pagespeed_checker.py
wagtail_seotoolkit/core/utils/checkers/placeholder_checker.py
wagtail_seotoolkit/core/utils/checkers/schema_checker.py
wagtail_seotoolkit/core/utils/checkers/title_checker.py
wagtail_seotoolkit/management/__init__.py
wagtail_seotoolkit/management/commands/__init__.py
wagtail_seotoolkit/management/commands/run_scheduled_audits.py
wagtail_seotoolkit/management/commands/seoaudit.py
wagtail_seotoolkit/migrations/0001_initial.py
wagtail_seotoolkit/migrations/0002_seoauditissue_page.py
wagtail_seotoolkit/migrations/0003_alter_seoauditissue_issue_severity.py
wagtail_seotoolkit/migrations/0004_alter_seoauditrun_status.py
wagtail_seotoolkit/migrations/0005_seoauditissue_requires_dev_fix.py
wagtail_seotoolkit/migrations/0006_add_pagespeed_issue_types.py
wagtail_seotoolkit/migrations/0007_update_pagespeed_issue_type_names.py
wagtail_seotoolkit-0.2.3.dist-info/licenses/LICENSE
wagtail_seotoolkit-0.2.3.dist-info/licenses/LICENSE-MIT
wagtail_seotoolkit-0.2.3.dist-info/licenses/LICENSE-PROPRIETARY
wagtail_seotoolkit-0.2.3.dist-info/METADATA
wagtail_seotoolkit-0.2.3.dist-info/WHEEL
wagtail_seotoolkit-0.2.3.dist-info/top_level.txt
wagtail_seotoolkit-0.2.3.dist-info/RECORD
