Metadata-Version: 2.4
Name: wagtail-seotoolkit
Version: 0.2.3
Summary: A comprehensive SEO toolkit for Wagtail CMS (Dual License: MIT for core, Proprietary for pro features)
Author-email: WAYF <hello@wayfdigital.com>
Maintainer-email: WAYF <hello@wayfdigital.com>
License-Expression: MIT AND LicenseRef-Proprietary
Project-URL: Homepage, https://github.com/wayfdigital/wagtail-seotoolkit
Project-URL: Documentation, https://github.com/wayfdigital/wagtail-seotoolkit#readme
Project-URL: Repository, https://github.com/wayfdigital/wagtail-seotoolkit
Project-URL: Issues, https://github.com/wayfdigital/wagtail-seotoolkit/issues
Keywords: wagtail,django,seo,cms
Classifier: Development Status :: 4 - Beta
Classifier: Framework :: Django
Classifier: Framework :: Wagtail
Classifier: Framework :: Wagtail :: 5
Classifier: Framework :: Wagtail :: 6
Classifier: Framework :: Wagtail :: 7
Classifier: Intended Audience :: Developers
Classifier: Operating System :: OS Independent
Classifier: Programming Language :: Python
Classifier: Programming Language :: Python :: 3
Classifier: Programming Language :: Python :: 3.8
Classifier: Programming Language :: Python :: 3.9
Classifier: Programming Language :: Python :: 3.10
Classifier: Programming Language :: Python :: 3.11
Classifier: Programming Language :: Python :: 3.12
Classifier: Programming Language :: Python :: 3.13
Classifier: Topic :: Internet :: WWW/HTTP
Classifier: Topic :: Internet :: WWW/HTTP :: Dynamic Content
Requires-Python: >=3.8
License-File: LICENSE
License-File: LICENSE-MIT
License-File: LICENSE-PROPRIETARY
Requires-Dist: wagtail>=6.4.0
Requires-Dist: beautifulsoup4>=4.9.0
Requires-Dist: tqdm>=4.65.0
Provides-Extra: dev
Requires-Dist: black>=22.3.0; extra == "dev"
Requires-Dist: ruff>=0.0.290; extra == "dev"
Requires-Dist: pytest>=7.0; extra == "dev"
Requires-Dist: pytest-django>=4.5; extra == "dev"
Dynamic: license-file
